gadgit/GAInfo.py
gadgit/GAOutput.py
gadgit/GeneInfo.py
gadgit/__init__.py
gadgit/gadgit.py
gadgit/helpers/__init__.py
gadgit/helpers/make_centrality_frame.py
gadgit-0.7.0.dist-info/AUTHORS.rst
gadgit-0.7.0.dist-info/LICENSE
gadgit-0.7.0.dist-info/METADATA
gadgit-0.7.0.dist-info/WHEEL
gadgit-0.7.0.dist-info/top_level.txt
gadgit-0.7.0.dist-info/RECORD
