Metadata-Version: 2.1
Name: gadgit
Version: 0.7.0
Summary: Genetic Algorithm for Disease Gene Identification Toolbox
Home-page: https://github.com/Andesha/gadgit
Author: Tyler Collins
Author-email: tk11br@sharcnet.ca
License: MIT license
Keywords: gadgit
Platform: UNKNOWN
Classifier: Development Status :: 2 - Pre-Alpha
Classifier: Intended Audience :: Developers
Classifier: License :: OSI Approved :: MIT License
Classifier: Natural Language :: English
Classifier: Programming Language :: Python :: 3.7
Classifier: Programming Language :: Python :: 3.8
Requires-Python: >=3.5
License-File: LICENSE
License-File: AUTHORS.rst
Requires-Dist: deap
Requires-Dist: numpy
Requires-Dist: pandas
